pys5p/__init__.py
pys5p/ckd_io.py
pys5p/error_propagation.py
pys5p/get_data_dir.py
pys5p/icm_io.py
pys5p/l1b_io.py
pys5p/l1b_patch.py
pys5p/lv2_io.py
pys5p/ocm_io.py
pys5p/rls.py
pys5p/s5p_msm.py
pys5p/swir_region.py
pys5p/swir_texp.py
pys5p/version.py
pys5p/lib/__init__.py
pys5p-2.2.0.dist-info/LICENSE
pys5p-2.2.0.dist-info/METADATA
pys5p-2.2.0.dist-info/WHEEL
pys5p-2.2.0.dist-info/top_level.txt
pys5p-2.2.0.dist-info/RECORD
