Metadata-Version: 2.1
Name: pys5p
Version: 2.2.0
Summary: Software package to access Sentinel-5p Tropomi data products
Author-email: Richard van Hees <r.m.van.hees@sron.nl>, Paul Tol <P.J.J.Tol@sron.nl>
License: BSD-3-Clause
Project-URL: homepage, https://github.com/rmvanhees/pys5p
Project-URL: documentation, https://pys5p.readthedocs.io/en/latest/
Project-URL: Issue tracker, https://github.com/rmvanhees/pys5p/issues
Classifier: Development Status :: 5 - Production/Stable
Classifier: Intended Audience :: Developers
Classifier: Intended Audience :: Science/Research
Classifier: License :: OSI Approved :: BSD License
Classifier: Operating System :: OS Independent
Classifier: Programming Language :: Python :: 3 :: Only
Classifier: Programming Language :: Python :: 3.9
Classifier: Programming Language :: Python :: 3.10
Classifier: Programming Language :: Python :: 3.11
Classifier: Topic :: Scientific/Engineering :: Atmospheric Science
Requires-Python: >=3.9
License-File: LICENSE
Requires-Dist: h5py >=3.8
Requires-Dist: moniplot >=0.5.8
Requires-Dist: numpy >=1.24
Requires-Dist: netCDF4 >=1.5
Requires-Dist: xarray >=2023.3
Provides-Extra: toml
Requires-Dist: toml ; extra == 'toml'
